{
  "timestamp": "20260512_002737",
  "seed": 42,
  "params": {
    "signal_source": "latent",
    "signal_type": "linear",
    "spatial_autocorrelation": "medium",
    "snr": "medium",
    "tract_list_source": "auto"
  },
  "diagnostics": {
    "morans_i_achieved": 0.5966145097907107,
    "morans_i_target": 0.4,
    "morans_i_y_true": 0.16074047265232533,
    "within_tract_variance_ratio": 0.83296451614552,
    "signal_variance": 1.0,
    "residual_variance": 0.9999999999999998,
    "noise_variance": 1.0,
    "length_scale_per_tract": {
      "47065000600": 50.0,
      "47065000700": 67.7734375,
      "47065001200": 50.0,
      "47065001800": 50.5859375,
      "47065001900": 50.0,
      "47065002400": 50.0,
      "47065003400": 50.0,
      "47065010431": 50.0,
      "47065010433": 51.7578125,
      "47065010435": 53.7109375,
      "47065011311": 50.0,
      "47065011321": 50.0,
      "47065011324": 12000.0,
      "47065011325": 51.3671875,
      "47065011326": 50.0,
      "47065011402": 50.0,
      "47065011413": 70.1171875,
      "47065011444": 50.0,
      "47065011447": 58.7890625,
      "47065011900": 50.0
    },
    "n_addresses": 39535,
    "n_tracts": 20
  },
  "address_id_column": "address_hash",
  "raw_address_id_column": "hash",
  "feature_cache_path": "data/raw/address_features/combined_address_features.csv",
  "proj_crs": "EPSG:32616",
  "n20_tract_list_source": "output/m2_n20_recovery/summary/n20_tract_list.txt"
}